seaplane/gen/carrier/__init__.py
seaplane/gen/carrier/api_client.py
seaplane/gen/carrier/api_response.py
seaplane/gen/carrier/configuration.py
seaplane/gen/carrier/exceptions.py
seaplane/gen/carrier/py.typed
seaplane/gen/carrier/rest.py
seaplane/gen/carrier/api/__init__.py
seaplane/gen/carrier/api/endpoint_api.py
seaplane/gen/carrier/api/flow_api.py
seaplane/gen/carrier/api/key_value_api.py
seaplane/gen/carrier/api/object_api.py
seaplane/gen/carrier/api/stream_api.py
seaplane/gen/carrier/api/webhook_api.py
seaplane/gen/carrier/models/__init__.py
seaplane/gen/carrier/models/azure_blob_storage_output.py
seaplane/gen/carrier/models/azure_blob_storage_output_azure_blob_storage.py
seaplane/gen/carrier/models/broker.py
seaplane/gen/carrier/models/broker_broker.py
seaplane/gen/carrier/models/broker_broker_outputs_inner.py
seaplane/gen/carrier/models/bucket.py
seaplane/gen/carrier/models/carrier_input.py
seaplane/gen/carrier/models/carrier_input_config.py
seaplane/gen/carrier/models/carrier_output.py
seaplane/gen/carrier/models/carrier_output_config.py
seaplane/gen/carrier/models/carrier_stream.py
seaplane/gen/carrier/models/carrier_stream_details.py
seaplane/gen/carrier/models/carrier_stream_options.py
seaplane/gen/carrier/models/cors.py
seaplane/gen/carrier/models/docker_processor.py
seaplane/gen/carrier/models/docker_processor_docker.py
seaplane/gen/carrier/models/error.py
seaplane/gen/carrier/models/flow.py
seaplane/gen/carrier/models/get_store200_response.py
seaplane/gen/carrier/models/http_server.py
seaplane/gen/carrier/models/http_server_http_server.py
seaplane/gen/carrier/models/input.py
seaplane/gen/carrier/models/key_value_config.py
seaplane/gen/carrier/models/metadata_headers.py
seaplane/gen/carrier/models/object_stat.py
seaplane/gen/carrier/models/output.py
seaplane/gen/carrier/models/processor.py
seaplane/gen/carrier/models/secret.py
seaplane/gen/carrier/models/sql_raw.py
seaplane/gen/carrier/models/sql_raw_sql_raw.py
seaplane.api-0.0.15.dist-info/LICENSE
seaplane.api-0.0.15.dist-info/METADATA
seaplane.api-0.0.15.dist-info/WHEEL
seaplane.api-0.0.15.dist-info/top_level.txt
seaplane.api-0.0.15.dist-info/RECORD
