Metadata-Version: 2.1
Name: seaplane.api
Version: 0.0.15
Summary: Carrier API
Home-page: 
Author: Seaplane IO, Inc.
Author-email: support@seaplane.io
License: Apache 2.0
Keywords: OpenAPI,OpenAPI-Generator,Carrier API
License-File: LICENSE
Requires-Dist: urllib3 >=1.25.3
Requires-Dist: python-dateutil
Requires-Dist: pydantic <2,>=1.10.5
Requires-Dist: aenum
